simdyn/__init__.py
simdyn/base.py
simdyn/parameters.py
simdyn/integrators/__init__.py
simdyn/integrators/euler.py
simdyn/integrators/rk4.py
simdyn/systems/__init__.py
simdyn/systems/cartpole.py
simdyn/systems/double_integrator.py
simdyn/systems/pendulum.py
simdyn/systems/rocket3dof.py
simdyn/systems/rocket6dof.py
simdyn/systems/unicycle.py
simdyn/utils/__init__.py
simdyn/utils/quaternion.py
simdyn/utils/rotations.py
simdyn/visualization/__init__.py
simdyn/visualization/animate.py
simdyn/visualization/plotters.py
simdyn-0.1.0.dist-info/licenses/LICENSE
simdyn-0.1.0.dist-info/METADATA
simdyn-0.1.0.dist-info/WHEEL
simdyn-0.1.0.dist-info/top_level.txt
simdyn-0.1.0.dist-info/RECORD
