Metadata-Version: 2.4
Name: simdyn
Version: 0.1.0
Summary: A modular dynamics library for control systems research
Author: SimDyn Contributors
License: MIT
Project-URL: Homepage, https://github.com/shiivashaakeri/simdyn
Project-URL: Documentation, https://github.com/shiivashaakeri/simdyn#readme
Project-URL: Repository, https://github.com/shiivashaakeri/simdyn
Project-URL: Issues, https://github.com/shiivashaakeri/simdyn/issues
Keywords: dynamics,control systems,robotics,aerospace,simulation,trajectory optimization
Classifier: Development Status :: 3 - Alpha
Classifier: Intended Audience :: Science/Research
Classifier: License :: OSI Approved :: MIT License
Classifier: Programming Language :: Python :: 3
Classifier: Programming Language :: Python :: 3.10
Classifier: Programming Language :: Python :: 3.11
Classifier: Programming Language :: Python :: 3.12
Classifier: Topic :: Scientific/Engineering
Classifier: Topic :: Scientific/Engineering :: Physics
Requires-Python: >=3.10
License-File: LICENSE
Requires-Dist: numpy>=1.24.0
Requires-Dist: scipy>=1.10.0
Provides-Extra: viz
Requires-Dist: matplotlib>=3.7.0; extra == "viz"
Provides-Extra: dev
Requires-Dist: pytest>=7.0.0; extra == "dev"
Requires-Dist: pytest-cov>=4.0.0; extra == "dev"
Requires-Dist: black>=23.0.0; extra == "dev"
Requires-Dist: ruff>=0.1.0; extra == "dev"
Requires-Dist: mypy>=1.0.0; extra == "dev"
Provides-Extra: all
Requires-Dist: simdyn[dev,viz]; extra == "all"
Dynamic: license-file
